{"trial_id": "41c3f4c0408314a54fd3c0d671c5b69d", "hyperparameters": {"space": [{"class_name": "Int", "config": {"name": "LSTM_layers", "default": null, "conditions": [], "min_value": 0, "max_value": 2, "step": 1, "sampling": null}}, {"class_name": "Int", "config": {"name": "LSTM_last", "default": null, "conditions": [], "min_value": 1, "max_value": 55, "step": 1, "sampling": null}}, {"class_name": "Float", "config": {"name": "Dense_dropout", "default": 0.0, "conditions": [], "min_value": 0.0, "max_value": 0.9, "step": 0.1, "sampling": null}}, {"class_name": "Float", "config": {"name": "learning_rate", "default": 1e-06, "conditions": [], "min_value": 1e-06, "max_value": 0.001, "step": null, "sampling": "log"}}, {"class_name": "Int", "config": {"name": "LSTM_0", "default": null, "conditions": [], "min_value": 1, "max_value": 55, "step": 1, "sampling": null}}, {"class_name": "Float", "config": {"name": "lstm0_dropout", "default": 0.0, "conditions": [], "min_value": 0.0, "max_value": 0.9, "step": 0.1, "sampling": null}}, {"class_name": "Int", "config": {"name": "LSTM_1", "default": null, "conditions": [], "min_value": 1, "max_value": 55, "step": 1, "sampling": null}}, {"class_name": "Float", "config": {"name": "lstm1_dropout", "default": 0.0, "conditions": [], "min_value": 0.0, "max_value": 0.9, "step": 0.1, "sampling": null}}], "values": {"LSTM_layers": 2, "LSTM_last": 55, "Dense_dropout": 0.0, "learning_rate": 0.001, "LSTM_0": 55, "lstm0_dropout": 0.9, "LSTM_1": 55, "lstm1_dropout": 0.0}}, "metrics": {"metrics": {"loss": {"direction": "min", "observations": [{"value": [0.015264700166881084], "step": 0}]}, "rmse": {"direction": "min", "observations": [{"value": [0.09611684083938599], "step": 0}]}, "val_loss": {"direction": "min", "observations": [{"value": [0.02308616042137146], "step": 0}]}, "val_rmse": {"direction": "min", "observations": [{"value": [0.12138724327087402], "step": 0}]}}}, "score": 0.12138724327087402, "best_step": 0, "status": "COMPLETED"}