{"trial_id": "82c86c11fd4958acf302ac73420e1ebd", "hyperparameters": {"space": [{"class_name": "Int", "config": {"name": "LSTM_layers", "default": null, "conditions": [], "min_value": 1, "max_value": 2, "step": 1, "sampling": null}}, {"class_name": "Int", "config": {"name": "LSTM_0", "default": null, "conditions": [], "min_value": 1, "max_value": 55, "step": 1, "sampling": null}}, {"class_name": "Float", "config": {"name": "lstm0_dropout", "default": 0.0, "conditions": [], "min_value": 0.0, "max_value": 0.9, "step": 0.1, "sampling": null}}, {"class_name": "Int", "config": {"name": "LSTM_last", "default": null, "conditions": [], "min_value": 1, "max_value": 10, "step": 1, "sampling": null}}, {"class_name": "Float", "config": {"name": "Dense_dropout", "default": 0.0, "conditions": [], "min_value": 0.0, "max_value": 0.9, "step": 0.1, "sampling": null}}, {"class_name": "Float", "config": {"name": "lambda_l2", "default": 0.0, "conditions": [], "min_value": 0.0, "max_value": 0.005, "step": 0.0001, "sampling": null}}, {"class_name": "Float", "config": {"name": "learning_rate", "default": 0.0001, "conditions": [], "min_value": 0.0001, "max_value": 0.01, "step": null, "sampling": "log"}}, {"class_name": "Int", "config": {"name": "LSTM_1", "default": null, "conditions": [], "min_value": 1, "max_value": 55, "step": 1, "sampling": null}}, {"class_name": "Float", "config": {"name": "lstm1_dropout", "default": 0.0, "conditions": [], "min_value": 0.0, "max_value": 0.9, "step": 0.1, "sampling": null}}], "values": {"LSTM_layers": 1, "LSTM_0": 55, "lstm0_dropout": 0.7000000000000001, "LSTM_last": 9, "Dense_dropout": 0.0, "lambda_l2": 0.0014, "learning_rate": 0.009733797683418817, "LSTM_1": 50, "lstm1_dropout": 0.6000000000000001}}, "metrics": {"metrics": {"loss": {"direction": "min", "observations": [{"value": [0.2423584908246994], "step": 0}]}, "rmse": {"direction": "min", "observations": [{"value": [0.4174060821533203], "step": 0}]}, "val_loss": {"direction": "min", "observations": [{"value": [0.6235136985778809], "step": 0}]}, "val_rmse": {"direction": "min", "observations": [{"value": [0.7446876764297485], "step": 0}]}}}, "score": 0.7446876764297485, "best_step": 0, "status": "COMPLETED"}